{
    "categories_questions": [
      {
        "nom": "C'est-à-dire",
        "cartes": [
          {
            "theme": "Zissure",
            "questions": [
              {
                "niveau": 1,
                "question": "Zissure s'écrit avec un Z au début ou un W ?",
                "reponse": "Un Z"
              },
              {
                "niveau": 2,
                "question": "Une zissure est une façon de penser, une façon d'être ou une façon de dire moi ?",
                "reponse": "Une façon de dire moi"
              }
            ]
          }
        ]
      }
    ]
  }
  